vap_crewai/__init__.py
vap_crewai/tools.py
vap_crewai-0.2.1.dist-info/METADATA
vap_crewai-0.2.1.dist-info/WHEEL
vap_crewai-0.2.1.dist-info/RECORD
