Metadata-Version: 2.4
Name: vap-crewai
Version: 0.2.1
Summary: VAP CrewAI integration - Execution control for crews calling paid APIs
Project-URL: Homepage, https://vapagent.com
Project-URL: Documentation, https://api.vapagent.com/docs
Project-URL: Repository, https://github.com/elestirelbilinc-sketch/vap-showcase
Author-email: VAP Team <hello@vapagent.com>
License-Expression: MIT
Keywords: agents,ai,cost-control,crewai,execution-control,multi-agent,vap
Classifier: Development Status :: 4 - Beta
Classifier: Intended Audience :: Developers
Classifier: License :: OSI Approved :: MIT License
Classifier: Programming Language :: Python :: 3
Classifier: Programming Language :: Python :: 3.9
Classifier: Programming Language :: Python :: 3.10
Classifier: Programming Language :: Python :: 3.11
Classifier: Programming Language :: Python :: 3.12
Classifier: Topic :: Multimedia :: Sound/Audio
Classifier: Topic :: Multimedia :: Video
Classifier: Topic :: Software Development :: Libraries :: Python Modules
Requires-Python: >=3.9
Requires-Dist: crewai>=0.1.0
Requires-Dist: vap-sdk>=0.1.0
